mp3_duration/__init__.py
mp3_duration/__main__.py
mp3_duration/cli.py
mp3_duration/mp3_duration.py
remote_mp3_duration-0.1.0.dist-info/LICENSE
remote_mp3_duration-0.1.0.dist-info/METADATA
remote_mp3_duration-0.1.0.dist-info/WHEEL
remote_mp3_duration-0.1.0.dist-info/entry_points.txt
remote_mp3_duration-0.1.0.dist-info/top_level.txt
remote_mp3_duration-0.1.0.dist-info/RECORD
