Metadata-Version: 2.1
Name: remote_mp3_duration
Version: 0.1.0
Home-page: https://github.com/yihong0618/remote_mp3_duration
Author: yihong0618
Author-email: zouzou0208@gmail.com
License: MIT
License-File: LICENSE
Requires-Dist: requests
